zmlx/__init__.py
zmlx/_compat.py
zmlx/api.py
zmlx/autograd.py
zmlx/autotune.py
zmlx/cache.py
zmlx/codegen.py
zmlx/device.py
zmlx/device_profile.py
zmlx/elementwise.py
zmlx/ir.py
zmlx/ir_build.py
zmlx/jit_compiler.py
zmlx/metal.py
zmlx/msl.py
zmlx/nn.py
zmlx/optimizers.py
zmlx/profile.py
zmlx/registry.py
zmlx/rowwise.py
zmlx/testing.py
zmlx/validate.py
zmlx/bench/__init__.py
zmlx/bench/__main__.py
zmlx/bench/report.py
zmlx/kernels/__init__.py
zmlx/kernels/activations.py
zmlx/kernels/attention.py
zmlx/kernels/bits.py
zmlx/kernels/fused.py
zmlx/kernels/fused_moe.py
zmlx/kernels/image.py
zmlx/kernels/indexing.py
zmlx/kernels/linear.py
zmlx/kernels/loss.py
zmlx/kernels/moe.py
zmlx/kernels/norms.py
zmlx/kernels/optimizers.py
zmlx/kernels/quant.py
zmlx/kernels/reductions.py
zmlx/kernels/rope.py
zmlx/kernels/scan.py
zmlx/kernels/softmax.py
zmlx/kernels/transformer.py
zmlx/kernels/vlsp.py
zmlx/patch/__init__.py
zmlx/patch/_modules.py
zmlx/patch/_registry.py
zmlx/patch/_traversal.py
zmlx/patch/_types.py
zmlx/patch/patterns/__init__.py
zmlx/patch/patterns/geglu_mlp.py
zmlx/patch/patterns/layernorm.py
zmlx/patch/patterns/moe_mlp.py
zmlx/patch/patterns/residual_norm.py
zmlx/patch/patterns/rmsnorm.py
zmlx/patch/patterns/softmax.py
zmlx/patch/patterns/swiglu_mlp.py
zmlx/train/__init__.py
zmlx/train/callbacks.py
zmlx/train/cli.py
zmlx/train/config.py
zmlx/train/export.py
zmlx/train/loss.py
zmlx/train/runner.py
zmlx-0.7.11.dist-info/METADATA
zmlx-0.7.11.dist-info/WHEEL
zmlx-0.7.11.dist-info/entry_points.txt
zmlx-0.7.11.dist-info/licenses/LICENSE
zmlx-0.7.11.dist-info/RECORD
