Metadata-Version: 2.4
Name: zmlx
Version: 0.7.11
Summary: ZMLX: Metal-kernel toolkit and optimization lab for MLX on Apple Silicon. Fused MoE decode (+5-12% on LFM2-8B-A1B), custom GPU kernels in one line, 70+ kernel catalog.
Project-URL: Homepage, https://github.com/Hmbown/ZMLX
Project-URL: Repository, https://github.com/Hmbown/ZMLX
Project-URL: Documentation, https://github.com/Hmbown/ZMLX#readme
Project-URL: Issues, https://github.com/Hmbown/ZMLX/issues
Project-URL: Changelog, https://github.com/Hmbown/ZMLX/blob/main/CHANGELOG.md
Author: Hunter Bown
License: MIT
License-File: LICENSE
Keywords: apple-silicon,autograd,jit,kernels,metal,mlx,zmlx
Classifier: Development Status :: 3 - Alpha
Classifier: Intended Audience :: Developers
Classifier: License :: OSI Approved :: MIT License
Classifier: Operating System :: MacOS :: MacOS X
Classifier: Programming Language :: Python :: 3
Classifier: Programming Language :: Python :: 3 :: Only
Classifier: Programming Language :: Python :: 3.10
Classifier: Programming Language :: Python :: 3.11
Classifier: Programming Language :: Python :: 3.12
Classifier: Topic :: Scientific/Engineering :: Artificial Intelligence
Classifier: Topic :: Software Development :: Libraries
Requires-Python: >=3.10
Requires-Dist: mlx>=0.30.0
Provides-Extra: dev
Requires-Dist: mypy>=1.10.0; extra == 'dev'
Requires-Dist: numpy>=1.24.0; extra == 'dev'
Requires-Dist: pytest>=8.0.0; extra == 'dev'
Requires-Dist: pyyaml>=6.0; extra == 'dev'
Requires-Dist: ruff>=0.5.0; extra == 'dev'
Requires-Dist: types-pyyaml>=6.0; extra == 'dev'
Provides-Extra: train
Requires-Dist: huggingface-hub>=0.20.0; extra == 'train'
Requires-Dist: mlx-lm>=0.25.0; extra == 'train'
Requires-Dist: pyyaml>=6.0; extra == 'train'
Requires-Dist: transformers>=4.40.0; extra == 'train'
